xlsz-0.0.1.dist-info/METADATA
xlsz-0.0.1.dist-info/WHEEL
xlsz-0.0.1.dist-info/license_files/LICENSE
xlsz/_xlsx.pyi
xlsz/__init__.py
xlsz/py.typed
xlsz/_xlsx.cpython-312-aarch64-linux-gnu.so
xlsz-0.0.1.dist-info/RECORD
