Metadata-Version: 2.1
Name: xlsz
Version: 0.0.1
License-File: LICENSE
Summary: xlsx file reader/writer
Author-email: zztkm <zztkm@tsurutatakumi.info>
Requires-Python: >=3.8
